README.rst
setup.py
exp100/__init__.py
exp100/exp100.py
exp100.egg-info/PKG-INFO
exp100.egg-info/SOURCES.txt
exp100.egg-info/dependency_links.txt
exp100.egg-info/entry_points.txt
exp100.egg-info/top_level.txt