Metadata-Version: 1.1
Name: exp100
Version: 0.0.1
Summary: I'm a small script that help you get express package information use kuaidi100.com api.
Home-page: http://www.iloveplum.in/
Author: Chris
Author-email: luohuawoaini@gmail.com
License: MIT
Keywords: internet,query,express,http
Platform: UNKNOWN
Classifier: Development Status :: 3 - Alpha
Classifier: Environment :: Web Environment
Classifier: Intended Audience :: Information Technology
Classifier: Intended Audience :: End Users/Desktop
Classifier: License :: OSI Approved :: MIT License
Classifier: Operating System :: OS Independent
Classifier: Programming Language :: Python
Classifier: Topic :: Internet :: WWW/HTTP
